{
  "nova_ultra_config": {
    "version": "2.0.0",
    "ui_theme": "ultra_professional",
    "enable_animations": true,
    "enable_voice": true,
    "enable_glassmorphism": true,
    "auto_agent_detection": true,
    "real_time_updates": true,
    "keyboard_shortcuts": true,
    "premium_features": {
      "azure_voice": true,
      "web_search": true,
      "image_generation": true,
      "github_integration": true,
      "file_processing": true,
      "crypto_tracking": true,
      "weather_service": true
    },
    "display_settings": {
      "sidebar_width": 32,
      "status_panel_width": 28,
      "chat_animation_speed": 0.3,
      "typing_indicator": true,
      "gradient_backgrounds": true,
      "neon_effects": true
    },
    "agent_settings": {
      "coding_expert": {
        "enabled": true,
        "icon": "\ud83d\udd27"
      },
      "career_coach": {
        "enabled": true,
        "icon": "\ud83d\udcbc"
      },
      "business_consultant": {
        "enabled": true,
        "icon": "\ud83d\udcc8"
      },
      "medical_advisor": {
        "enabled": true,
        "icon": "\ud83c\udfe5"
      },
      "emotional_counselor": {
        "enabled": true,
        "icon": "\ud83d\udc99"
      },
      "technical_architect": {
        "enabled": true,
        "icon": "\ud83d\ude80"
      }
    }
  }
}